[
  {
    "timestamp": "2025-04-12T17:45:22.740000+00:00",
    "action_type": "click",
    "click_type": "nav_bar",
    "category": "navigation",
    "product": "{\"name\": \"\", \"data\": \"\"}",
    "delay_from_previous_sec": 0
  },
  {
    "timestamp": "2025-04-12T17:45:35.847000+00:00",
    "action_type": "scroll",
    "click_type": "nan",
    "category": "navigation",
    "product": "nan",
    "delay_from_previous_sec": 13.107
  },
  {
    "timestamp": "2025-04-12T17:45:50.692000+00:00",
    "action_type": "scroll",
    "click_type": "nan",
    "category": "navigation",
    "product": "nan",
    "delay_from_previous_sec": 14.845
  },
  {
    "timestamp": "2025-04-12T17:45:55.421000+00:00",
    "action_type": "click",
    "click_type": "other",
    "category": "navigation",
    "product": "{\"name\": \"\", \"data\": \"\"}",
    "delay_from_previous_sec": 4.729
  },
  {
    "timestamp": "2025-04-12T17:59:02.341000+00:00",
    "action_type": "tab_activate",
    "click_type": "nan",
    "category": "navigation",
    "product": "nan",
    "delay_from_previous_sec": 786.92
  },
  {
    "timestamp": "2025-04-12T17:59:03.217000+00:00",
    "action_type": "scroll",
    "click_type": "nan",
    "category": "navigation",
    "product": "nan",
    "delay_from_previous_sec": 0.876
  },
  {
    "timestamp": "2025-04-12T18:40:47.006000+00:00",
    "action_type": "tab_activate",
    "click_type": "nan",
    "category": "navigation",
    "product": "nan",
    "delay_from_previous_sec": 2503.789
  },
  {
    "timestamp": "2025-04-12T18:40:50.405000+00:00",
    "action_type": "scroll",
    "click_type": "nan",
    "category": "navigation",
    "product": "nan",
    "delay_from_previous_sec": 3.399
  },
  {
    "timestamp": "2025-04-12T18:44:07.239000+00:00",
    "action_type": "scroll",
    "click_type": "nan",
    "category": "navigation",
    "product": "nan",
    "delay_from_previous_sec": 196.834
  },
  {
    "timestamp": "2025-04-12T18:44:07.989000+00:00",
    "action_type": "scroll",
    "click_type": "nan",
    "category": "navigation",
    "product": "nan",
    "delay_from_previous_sec": 0.75
  },
  {
    "timestamp": "2025-04-12T18:44:35.169000+00:00",
    "action_type": "tab_activate",
    "click_type": "nan",
    "category": "navigation",
    "product": "nan",
    "delay_from_previous_sec": 27.18
  },
  {
    "timestamp": "2025-04-12T18:45:07.533000+00:00",
    "action_type": "tab_activate",
    "click_type": "nan",
    "category": "navigation",
    "product": "nan",
    "delay_from_previous_sec": 32.364
  },
  {
    "timestamp": "2025-04-12T18:46:48.284000+00:00",
    "action_type": "tab_activate",
    "click_type": "nan",
    "category": "navigation",
    "product": "nan",
    "delay_from_previous_sec": 100.751
  },
  {
    "timestamp": "2025-04-12T18:47:25.523000+00:00",
    "action_type": "scroll",
    "click_type": "nan",
    "category": "navigation",
    "product": "nan",
    "delay_from_previous_sec": 37.239
  },
  {
    "timestamp": "2025-04-12T18:47:26.196000+00:00",
    "action_type": "scroll",
    "click_type": "nan",
    "category": "navigation",
    "product": "nan",
    "delay_from_previous_sec": 0.673
  },
  {
    "timestamp": "2025-04-12T18:59:30.307000+00:00",
    "action_type": "navigation",
    "click_type": "nan",
    "category": "navigation",
    "product": "nan",
    "delay_from_previous_sec": 724.111
  },
  {
    "timestamp": "2025-04-12T18:59:35.391000+00:00",
    "action_type": "click",
    "click_type": "product_option",
    "category": "navigation",
    "product": "{\"name\": \"product_options\", \"data\": \"{\\\"Size\\\":\\\"6",
    "delay_from_previous_sec": 5.084
  },
  {
    "timestamp": "2025-04-12T18:59:44.391000+00:00",
    "action_type": "tab_activate",
    "click_type": "nan",
    "category": "navigation",
    "product": "nan",
    "delay_from_previous_sec": 9.0
  },
  {
    "timestamp": "2025-04-12T18:59:57.715000+00:00",
    "action_type": "tab_activate",
    "click_type": "nan",
    "category": "navigation",
    "product": "nan",
    "delay_from_previous_sec": 13.324
  },
  {
    "timestamp": "2025-04-12T19:00:49.594000+00:00",
    "action_type": "tab_activate",
    "click_type": "nan",
    "category": "navigation",
    "product": "nan",
    "delay_from_previous_sec": 51.879
  },
  {
    "timestamp": "2025-04-12T19:01:01.489000+00:00",
    "action_type": "tab_activate",
    "click_type": "nan",
    "category": "navigation",
    "product": "nan",
    "delay_from_previous_sec": 11.895
  },
  {
    "timestamp": "2025-04-12T19:05:41.556000+00:00",
    "action_type": "tab_activate",
    "click_type": "nan",
    "category": "navigation",
    "product": "nan",
    "delay_from_previous_sec": 280.067
  },
  {
    "timestamp": "2025-04-12T19:05:44.501000+00:00",
    "action_type": "tab_activate",
    "click_type": "nan",
    "category": "navigation",
    "product": "nan",
    "delay_from_previous_sec": 2.945
  },
  {
    "timestamp": "2025-04-12T19:05:48.860000+00:00",
    "action_type": "tab_activate",
    "click_type": "nan",
    "category": "navigation",
    "product": "nan",
    "delay_from_previous_sec": 4.359
  },
  {
    "timestamp": "2025-04-12T19:06:24.823000+00:00",
    "action_type": "tab_activate",
    "click_type": "nan",
    "category": "navigation",
    "product": "nan",
    "delay_from_previous_sec": 35.963
  },
  {
    "timestamp": "2025-04-12T19:07:47.395000+00:00",
    "action_type": "tab_activate",
    "click_type": "nan",
    "category": "navigation",
    "product": "nan",
    "delay_from_previous_sec": 82.572
  },
  {
    "timestamp": "2025-04-12T20:02:54.135000+00:00",
    "action_type": "tab_activate",
    "click_type": "nan",
    "category": "navigation",
    "product": "nan",
    "delay_from_previous_sec": 3306.74
  },
  {
    "timestamp": "2025-04-12T20:02:57.619000+00:00",
    "action_type": "click",
    "click_type": "product_option",
    "category": "navigation",
    "product": "{\"name\": \"product_options\", \"data\": \"{\\\"Size\\\":\\\"1",
    "delay_from_previous_sec": 3.484
  },
  {
    "timestamp": "2025-04-12T20:03:33.508000+00:00",
    "action_type": "click",
    "click_type": "review",
    "category": "research",
    "product": "{\"name\": \"\", \"data\": \"\"}",
    "delay_from_previous_sec": 35.889
  },
  {
    "timestamp": "2025-04-12T20:04:33.769000+00:00",
    "action_type": "tab_activate",
    "click_type": "nan",
    "category": "navigation",
    "product": "nan",
    "delay_from_previous_sec": 60.261
  },
  {
    "timestamp": "2025-04-12T20:26:55.397000+00:00",
    "action_type": "tab_activate",
    "click_type": "nan",
    "category": "navigation",
    "product": "nan",
    "delay_from_previous_sec": 1341.628
  },
  {
    "timestamp": "2025-04-12T20:53:08.281000+00:00",
    "action_type": "tab_activate",
    "click_type": "nan",
    "category": "navigation",
    "product": "nan",
    "delay_from_previous_sec": 1572.884
  },
  {
    "timestamp": "2025-04-12T20:53:10.014000+00:00",
    "action_type": "click",
    "click_type": "product_option",
    "category": "navigation",
    "product": "{\"name\": \"product_options\", \"data\": \"{\\\"Size\\\":\\\"6",
    "delay_from_previous_sec": 1.733
  },
  {
    "timestamp": "2025-04-12T20:53:47.467000+00:00",
    "action_type": "tab_activate",
    "click_type": "nan",
    "category": "navigation",
    "product": "nan",
    "delay_from_previous_sec": 37.453
  },
  {
    "timestamp": "2025-04-12T20:56:27.181000+00:00",
    "action_type": "tab_activate",
    "click_type": "nan",
    "category": "navigation",
    "product": "nan",
    "delay_from_previous_sec": 159.714
  },
  {
    "timestamp": "2025-04-12T20:58:37.087000+00:00",
    "action_type": "tab_activate",
    "click_type": "nan",
    "category": "navigation",
    "product": "nan",
    "delay_from_previous_sec": 129.906
  },
  {
    "timestamp": "2025-04-12T20:58:40.171000+00:00",
    "action_type": "click",
    "click_type": "product_option",
    "category": "navigation",
    "product": "{\"name\": \"product_options\", \"data\": \"{\\\"Style\\\":\\\"",
    "delay_from_previous_sec": 3.084
  },
  {
    "timestamp": "2025-04-12T20:58:48.873000+00:00",
    "action_type": "scroll",
    "click_type": "nan",
    "category": "navigation",
    "product": "nan",
    "delay_from_previous_sec": 8.702
  },
  {
    "timestamp": "2025-04-12T20:58:50.112000+00:00",
    "action_type": "scroll",
    "click_type": "nan",
    "category": "navigation",
    "product": "nan",
    "delay_from_previous_sec": 1.2389999999999999
  },
  {
    "timestamp": "2025-04-12T20:58:51.040000+00:00",
    "action_type": "click",
    "click_type": "product_option",
    "category": "navigation",
    "product": "{\"name\": \"product_options\", \"data\": \"{\\\"Size\\\":\\\"6",
    "delay_from_previous_sec": 0.928
  },
  {
    "timestamp": "2025-04-12T20:59:39.636000+00:00",
    "action_type": "tab_activate",
    "click_type": "nan",
    "category": "navigation",
    "product": "nan",
    "delay_from_previous_sec": 48.596
  },
  {
    "timestamp": "2025-04-12T20:59:41.893000+00:00",
    "action_type": "click",
    "click_type": "product_option",
    "category": "navigation",
    "product": "{\"name\": \"product_options\", \"data\": \"{\\\"Style\\\":\\\"",
    "delay_from_previous_sec": 2.257
  },
  {
    "timestamp": "2025-04-12T21:01:44.560000+00:00",
    "action_type": "tab_activate",
    "click_type": "nan",
    "category": "navigation",
    "product": "nan",
    "delay_from_previous_sec": 122.667
  },
  {
    "timestamp": "2025-04-12T21:03:56.879000+00:00",
    "action_type": "tab_activate",
    "click_type": "nan",
    "category": "navigation",
    "product": "nan",
    "delay_from_previous_sec": 132.319
  },
  {
    "timestamp": "2025-04-12T21:05:12.343000+00:00",
    "action_type": "tab_activate",
    "click_type": "nan",
    "category": "navigation",
    "product": "nan",
    "delay_from_previous_sec": 75.464
  },
  {
    "timestamp": "2025-04-12T21:05:19.799000+00:00",
    "action_type": "tab_activate",
    "click_type": "nan",
    "category": "navigation",
    "product": "nan",
    "delay_from_previous_sec": 7.456
  },
  {
    "timestamp": "2025-04-12T21:05:35.142000+00:00",
    "action_type": "scroll",
    "click_type": "nan",
    "category": "navigation",
    "product": "nan",
    "delay_from_previous_sec": 15.343
  },
  {
    "timestamp": "2025-04-12T21:05:45.951000+00:00",
    "action_type": "click",
    "click_type": "product_option",
    "category": "navigation",
    "product": "{\"name\": \"product_options\", \"data\": \"{\\\"Style\\\":\\\"",
    "delay_from_previous_sec": 10.809
  },
  {
    "timestamp": "2025-04-12T21:06:03.839000+00:00",
    "action_type": "click",
    "click_type": "product_option",
    "category": "navigation",
    "product": "{\"name\": \"product_options\", \"data\": \"{\\\"Size\\\":\\\"6",
    "delay_from_previous_sec": 17.888
  },
  {
    "timestamp": "2025-04-12T21:06:47.376000+00:00",
    "action_type": "tab_activate",
    "click_type": "nan",
    "category": "navigation",
    "product": "nan",
    "delay_from_previous_sec": 43.537
  },
  {
    "timestamp": "2025-04-12T21:07:46.909000+00:00",
    "action_type": "scroll",
    "click_type": "nan",
    "category": "navigation",
    "product": "nan",
    "delay_from_previous_sec": 59.533
  },
  {
    "timestamp": "2025-04-12T21:07:47.798000+00:00",
    "action_type": "scroll",
    "click_type": "nan",
    "category": "navigation",
    "product": "nan",
    "delay_from_previous_sec": 0.889
  },
  {
    "timestamp": "2025-04-12T21:08:51.593000+00:00",
    "action_type": "tab_activate",
    "click_type": "nan",
    "category": "navigation",
    "product": "nan",
    "delay_from_previous_sec": 63.795
  },
  {
    "timestamp": "2025-04-12T21:10:18.060000+00:00",
    "action_type": "tab_activate",
    "click_type": "nan",
    "category": "navigation",
    "product": "nan",
    "delay_from_previous_sec": 86.467
  },
  {
    "timestamp": "2025-04-12T21:10:22.418000+00:00",
    "action_type": "tab_activate",
    "click_type": "nan",
    "category": "navigation",
    "product": "nan",
    "delay_from_previous_sec": 4.358
  },
  {
    "timestamp": "2025-04-12T21:10:23.043000+00:00",
    "action_type": "scroll",
    "click_type": "nan",
    "category": "navigation",
    "product": "nan",
    "delay_from_previous_sec": 0.625
  },
  {
    "timestamp": "2025-04-12T21:10:25.789000+00:00",
    "action_type": "click",
    "click_type": "product_option",
    "category": "navigation",
    "product": "{\"name\": \"product_options\", \"data\": \"{\\\"Size\\\":\\\"1",
    "delay_from_previous_sec": 2.746
  },
  {
    "timestamp": "2025-04-12T21:10:46.250000+00:00",
    "action_type": "scroll",
    "click_type": "nan",
    "category": "navigation",
    "product": "nan",
    "delay_from_previous_sec": 20.461
  },
  {
    "timestamp": "2025-04-12T21:10:48.116000+00:00",
    "action_type": "scroll",
    "click_type": "nan",
    "category": "navigation",
    "product": "nan",
    "delay_from_previous_sec": 1.866
  },
  {
    "timestamp": "2025-04-12T21:10:52.546000+00:00",
    "action_type": "scroll",
    "click_type": "nan",
    "category": "navigation",
    "product": "nan",
    "delay_from_previous_sec": 4.43
  },
  {
    "timestamp": "2025-04-12T21:11:00.316000+00:00",
    "action_type": "click",
    "click_type": "product_option",
    "category": "navigation",
    "product": "{\"name\": \"product_options\", \"data\": \"{\\\"Style\\\":\\\"",
    "delay_from_previous_sec": 7.77
  },
  {
    "timestamp": "2025-04-12T21:11:03.487000+00:00",
    "action_type": "click",
    "click_type": "product_option",
    "category": "navigation",
    "product": "{\"name\": \"product_options\", \"data\": \"{\\\"Style\\\":\\\"",
    "delay_from_previous_sec": 3.171
  },
  {
    "timestamp": "2025-04-12T21:13:43.144000+00:00",
    "action_type": "tab_activate",
    "click_type": "nan",
    "category": "navigation",
    "product": "nan",
    "delay_from_previous_sec": 159.657
  },
  {
    "timestamp": "2025-04-12T21:14:34.232000+00:00",
    "action_type": "click",
    "click_type": "purchase",
    "category": "conversion",
    "product": "{\"name\": \"product_details\", \"data\": \"{\\\"asin\\\":\\\"B",
    "delay_from_previous_sec": 51.088
  }
]